dpmfa/__init__.py
dpmfa/components.py
dpmfa/model.py
dpmfa/simulator.py
tests/__init__.py
tests/test_consttransfers.py
tests/test_randomchoicetransfer.py
dpmfa-1.1.dist-info/LICENCE.md
dpmfa-1.1.dist-info/METADATA
dpmfa-1.1.dist-info/WHEEL
dpmfa-1.1.dist-info/top_level.txt
dpmfa-1.1.dist-info/RECORD
