Metadata-Version: 2.1
Name: dpmfa
Version: 1.1
Summary: Dynamic probabilistic material flow analysis simulator
Home-page: https://github.com/isr-ifi/dpmfa
Author: ISR - UZH
Author-email: goncalves@ifi.uzh.ch
License: UNKNOWN
Platform: UNKNOWN
Classifier: Programming Language :: Python :: 3
Classifier: Operating System :: OS Independent
Requires-Python: >=3.6
